mao_mcp_test_01/__init__.py
mao_mcp_test_01/server.py
mao_mcp_test_01-0.2.0.dist-info/METADATA
mao_mcp_test_01-0.2.0.dist-info/WHEEL
mao_mcp_test_01-0.2.0.dist-info/entry_points.txt
mao_mcp_test_01-0.2.0.dist-info/top_level.txt
mao_mcp_test_01-0.2.0.dist-info/RECORD
