Metadata-Version: 2.4
Name: mao-mcp-test-01
Version: 0.2.0
Summary: mao test
Author-email: mao li <1437935584@qq.com>
License: MIT
Requires-Python: >=3.13
Requires-Dist: mcp
